LICENSE
MANIFEST.in
README.rst
setup.py
flask_orator/__init__.py
flask_orator/version.py
flask_orator.egg-info/PKG-INFO
flask_orator.egg-info/SOURCES.txt
flask_orator.egg-info/dependency_links.txt
flask_orator.egg-info/pbr.json
flask_orator.egg-info/requires.txt
flask_orator.egg-info/top_level.txt