Metadata-Version: 1.1
Name: flask-orator
Version: 0.1
Summary: Adds Orator support to your Flask application
Home-page: https://github.com/sdispater/orator
Author: Sébastien Eustace
Author-email: sebastien.eustace@gmail.com
License: MIT
Download-URL: https://github.com/sdispater/orator/archive/0.1.tar.gz
Platform: UNKNOWN
Classifier: Intended Audience :: Developers
Classifier: Operating System :: OS Independent
Classifier: Programming Language :: Python
Classifier: Topic :: Software Development :: Libraries :: Python Modules
